SR23002UNO/_init_.py
SR23002UNO/biseccion.py
SR23002UNO/crammer.py
SR23002UNO/descomposicion_lu.py
SR23002UNO/eliminacion_gauss.py
SR23002UNO/gauss_jordan.py
SR23002UNO/gauss_seidel.py
SR23002UNO/jacobi.py
sr23002uno-1.0.7.dist-info/METADATA
sr23002uno-1.0.7.dist-info/WHEEL
sr23002uno-1.0.7.dist-info/top_level.txt
sr23002uno-1.0.7.dist-info/RECORD
