Metadata-Version: 2.4
Name: SR23002UNO
Version: 1.0.7
Summary: Liberia para resolver ecuaciones lineales y no lineales
Home-page: https://github.com/sr230002/CDA135-GT02-SR23002UNO
Author: David Enrique Sixco Ramos
Author-email: sr23002@ues.edu.sv
License: MIT
Requires-Dist: numpy
Dynamic: author
Dynamic: author-email
Dynamic: description
Dynamic: description-content-type
Dynamic: home-page
Dynamic: license
Dynamic: requires-dist
Dynamic: summary
